{"ADDI_age": "41.39629629629629", "diagnosis_2": "Kidney cancer", "storyID": "STY1654210172", "Narrative": "Il Mondiale Rally tornare a far rombare i motori. Nel weekend si corre infatti tra le strade sterrate del Rally Italia Sardegna, quinta tappa di un campionato WRC 2022 che sta vedendo nel giovanissimo di casa Toyota, Kalle Rovanpera, uno dei pi\u00f9 grandi e attesi interpreti della nuova era delle auto ibride Rally1. La gara \u00e8 gi\u00e0 iniziata gioved\u00ec con il primo shakedown e le Prove Super Speciale Olbia-Cabu Abbas, ma \u00e8 certamente a \npartire da oggi che l\u2019appuntamento, che consta di oltre 300km di prove speciali, entra davvero nel vivo sulle strade di casa nostra\u2026 Qualcuno riuscir\u00e0 a interrompere il dominio del giovanissimo figlio d\u2019arte di casa Toyota, vincitore degli ultimi tre rally iridati?\n\nFoto: Instagram officialwrc", "least_likely_activity": "Tools", "ADI_sex": "26.211111111111126", "DDI_age": "28.392592592592596", "diagnosis_3": "Botulism", "diagnosis_1": "Medication reaction", "userPrimaryID": "20802", "most_likely_activity": "Food", "Media": "https://image.pixstory.com/Pixstory-image-16542101074034.jpeg", "Interest": "wrc, rally, sport", "GLAAD": "False", "Gender": "male", "Age": "33", "accountCreateDte": "2022-01-13", "ADI_age": "36.71666666666667", "DDI_sex": "22.607407407407408", "userID": "USR1642092657", "Title": "WRC, entra oggi nel vivo il Rally Italia Sardegna", "storyPrimaryID": "104386", "sarc": "False", "median_activity": "Food", "ADDI_sex": "31.20555555555555", "sport_event": "['Africa Cup of Nations']", "ADL": "False", "id": "0175ccfd-849d-4f74-bf43-b987f21520e6", "Festivals": "", "jaccard_score": 4.553391138050063e-05}