{"DDI_age": "37.324074074074076", "Narrative": "\u09ac\u09bf\u09ae\u09be\u09a8 \u09ac\u09be\u0982\u09b2\u09be\u09a6\u09c7\u09b6 \u098f\u09df\u09be\u09b0\u09b2\u09be\u0987\u09a8\u09cd\u09b8\u09c7\u09b0 \u09a6\u09c1\u099f\u09cb \u0989\u09dc\u09cb\u099c\u09be\u09b9\u09be\u099c\u09c7\u09b0 \u09ae\u09a7\u09cd\u09af\u09c7 \u0986\u09ac\u09be\u09b0\u0993 \u09b8\u0982\u0998\u09b0\u09cd\u09b7 \u0998\u099f\u09c7\u099b\u09c7\u0964 \u098f\u09a4\u09c7 \u09ac\u09bf\u09ae\u09be\u09a8\u09c7\u09b0 \u0989\u09dc\u09cb\u099c\u09be\u09b9\u09be\u099c \u09ac\u09cb\u09df\u09bf\u0982-\u09ed\u09ee\u09ed \u098f\u09ac\u0982 \u09ac\u09cb\u09df\u09bf\u0982-\u09ed\u09e9\u09ed \u098f\u09b0 \u09a1\u09be\u09a8\u09be \u0995\u09cd\u09b7\u09a4\u09bf\u0997\u09cd\u09b0\u09b8\u09cd\u09a4 \u09b9\u09df\u09c7\u099b\u09c7\u0964 \n\nhttps://bengali.nenow.in/bangladesh/biman-jets-collide-again-at-dhaka-airport-hanger\n\n\u09b0\u09ac\u09bf\u09ac\u09be\u09b0 \u09b0\u09be\u09a4 \u09b8\u09cb\u09df\u09be \u09ef\u099f\u09be\u09df \u09a2\u09be\u0995\u09be\u09b0 \u09b9\u09af\u09b0\u09a4 \u09b6\u09be\u09b9\u099c\u09be\u09b2\u09be\u09b2 \u0986\u09a8\u09cd\u09a4\u09b0\u09cd\u099c\u09be\u09a4\u09bf\u0995 \u09ac\u09bf\u09ae\u09be\u09a8\u09ac\u09a8\u09cd\u09a6\u09b0\u09c7\u09b0 \u09b9\u09cd\u09af\u09be\u0999\u09cd\u0997\u09be\u09b0\u09c7 \u09ac\u09cb\u09df\u09bf\u0982 \u09ed\u09ee\u09ed \u09a1\u09cd\u09b0\u09bf\u09ae\u09b2\u09be\u0987\u09a8\u09be\u09b0\u09c7\u09b0 \u09a1\u09be\u09a8\u09be\u09df (\u0989\u0987\u0982) \u09ac\u09bf\u09ae\u09be\u09a8\u09c7\u09b0\u0987 \u0986\u09b0\u09c7\u0995\u099f\u09bf \u09ed\u09e9\u09ed \u0989\u09dc\u09cb\u099c\u09be\u09b9\u09be\u099c\u09c7\u09b0 \u09a1\u09be\u09a8\u09be \u0986\u0998\u09be\u09a4 \u0995\u09b0\u09c7\u0964", "diagnosis_2": "Carbon monoxide poisoning", "Age": "21", "Media": "https://image.pixstory.com/Pixstory-image-165694887268880.png", "ADI_sex": "26.211111111111126", "most_likely_activity": "Health", "diagnosis_1": "Alcohol", "sport_event": "['World Championships (women)']", "Interest": "bangladesh", "ADDI_age": "49.88518518518518", "storyID": "STY1656949018", "least_likely_activity": "Writing", "accountCreateDte": "2021-12-02", "median_activity": "Health", "GLAAD": "False", "Gender": "male", "storyPrimaryID": "113266", "Festivals": "['A-Film Teens Fest - International Online Children and Youth Film Festival', 'Jean Rouch International Film Festival', 'Poitiers Film Festival']", "userID": "USR1638425715", "id": "0037997e-f6c6-47b2-891b-a054b93f176b", "DDI_sex": "22.607407407407408", "ADI_age": "42.805555555555564", "sarc": "False", "ADDI_sex": "31.20555555555555", "userPrimaryID": "11859", "Title": "\u09a2\u09be\u0995\u09be\u09df \u09e8 \u0989\u09dc\u09cb\u099c\u09be\u09b9\u09be\u099c\u09c7\u09b0 \u09ae\u09a7\u09cd\u09af\u09c7 \u0986\u09ac\u09be\u09b0\u0993 \u09b8\u0982\u0998\u09b0\u09cd\u09b7", "diagnosis_3": "Depression", "ADL": "False", "jaccard_score": 4.553391138050063e-05}