{"ADDI_age": "32.42619047619048", "userID": "USR1642421294", "DDI_age": "22.63095238095238", "diagnosis_1": "", "Interest": "Food, rajdhani", "storyID": "STY1642422007", "Media": "https://image.pixstory.com/Pixstory-image-164242131547691.png", "accountCreateDte": "2022-01-17", "most_likely_activity": "", "Age": "12", "ADI_sex": "30.177777777777784", "ADI_age": "27.866137566137564", "GLAAD": "False", "diagnosis_3": "", "Title": "Keep calm and drink milk.", "sport_event": "['Africa Cup of Nations', 'Australian Open']", "ADDI_sex": "34.87222222222221", "least_likely_activity": "", "sarc": "False", "storyPrimaryID": "71421", "Gender": "", "id": "0122a380-5483-4dde-9277-8531cab59f34", "Narrative": "A glass of milk before slep helps the swallow sorrows.", "DDI_sex": "24.34166666666667", "ADL": "False", "diagnosis_2": "", "Festivals": "", "median_activity": "", "userPrimaryID": "22744", "jaccard_score": 3.502608567730818e-05}