{"DDI_age": "37.324074074074076", "accountCreateDte": "2022-01-19", "diagnosis_1": "", "Age": "20", "ADDI_age": "49.88518518518518", "Title": "Car", "Narrative": "this is a very nice car", "most_likely_activity": "", "ADI_sex": "30.177777777777784", "GLAAD": "False", "diagnosis_3": "", "sport_event": "['Africa Cup of Nations', 'Australian Open']", "ADDI_sex": "34.87222222222221", "least_likely_activity": "", "storyPrimaryID": "72842", "Interest": "photography, car, sfsarsd", "ADI_age": "42.805555555555564", "sarc": "False", "userID": "USR1642610566", "Gender": "", "Media": "https://image.pixstory.com/Pixstory-image-164261093334925.png", "storyID": "STY1642611003", "userPrimaryID": "23690", "DDI_sex": "24.34166666666667", "id": "020cd7ac-92ec-4732-91c0-f42ee75da9fb", "ADL": "False", "diagnosis_2": "", "Festivals": "", "median_activity": "", "jaccard_score": 3.502608567730818e-05}