{"DDI_age": "25.175925925925913", "ADI_sex": "26.211111111111126", "storyID": "STY1644839677", "most_likely_activity": "Health", "accountCreateDte": "2022-01-17", "least_likely_activity": "Hunting", "diagnosis_3": "Carbon monoxide poisoning", "Narrative": "\u00c8 stata presentata a mezzogiorno, con un rapido video e delle immagini render svuluppate al computer, la AT03. Si tratta della nuova monoposto dell'AlphaTauri, scuderia di propriet\u00e0 della Red Bull ma con sede a Faenza, gi\u00e0 nota come Toro Rosso ed erede della mitica Minardi.\nAffidata come lo scorso anno alla coppia di piloti formata da Pierre Gasly e Yuki Tsunoda, la AT03 colpisce per la forma particolare delle prese d'aria sulle pance, molto pi\u00f9 quadrata rispetto alle altre vetture 2022 svelate finora.\nL'AlphaTauri lo scorso anno ha chiuso il Mondiale di F1 in sesta posizione, con 142 punti totali e un podio ottenuto da Gasly nel GP Azerbaijan, gara terminata al terzo posto.", "ADI_age": "33.07222222222222", "diagnosis_1": "Attention deficit hyperactivity disorder", "median_activity": "Health", "GLAAD": "False", "Gender": "male", "storyPrimaryID": "81320", "sport_event": "['Africa Cup of Nations', 'Australian Open']", "DDI_sex": "22.607407407407408", "userID": "USR1642425119", "Title": "Ecco la AT03, la monoposto 2022 dell'AlphaTauri", "Media": "https://image.pixstory.com/Pixstory-image-164483934263240.png", "sarc": "False", "ADDI_age": "37.23703703703705", "diagnosis_2": "Hemochromatosis", "Age": "40", "ADDI_sex": "31.20555555555555", "id": "0215c527-3d33-44e8-a210-6868bcb75dda", "Interest": "f1, formula 1, alphatauri", "userPrimaryID": "22770", "ADL": "False", "Festivals": "", "jaccard_score": 4.553391138050063e-05}