{"Festivals": "[\"Chicago International Children's Film Festival\", 'Doc NYC', 'Fort Lauderdale International Film Festival', 'New Orleans Film Festival', 'Philadelphia Jewish Film Festival', 'Seattle True Independent Film Festival']", "DDI_age": "25.175925925925913", "id": "007df097-3fcf-4cb5-9ba3-7604c7ca5ce1", "ADI_sex": "26.211111111111126", "Age": "44", "most_likely_activity": "Health", "diagnosis_3": "Botulism", "Media": "https://image.pixstory.com/Pixstory-image-165578874239819.png", "userPrimaryID": "21", "Narrative": "Wedding pictures are always happy frames. Such joy. Such happy moments of people coming together, talking to each other. \n\nEverything around is  made of sugar, spice and nice things that can only get nicer. \n\nHere's wishing Varsha and Alok a very happy married life", "userID": "USR1605632983", "Title": "Here's wishing my cousin Varsha and Alok a very happy married life", "ADI_age": "33.07222222222222", "median_activity": "Health", "GLAAD": "False", "Gender": "male", "DDI_sex": "22.607407407407408", "sarc": "False", "diagnosis_1": "Myocarditis", "ADDI_age": "37.23703703703705", "least_likely_activity": "Organizing", "diagnosis_2": "Hemochromatosis", "ADDI_sex": "31.20555555555555", "accountCreateDte": "2020-11-17", "storyPrimaryID": "108712", "Interest": "photography, wedding", "ADL": "False", "sport_event": "", "storyID": "STY1655788692", "jaccard_score": 4.553391138050063e-05}