{"DDI_age": "25.175925925925913", "accountCreateDte": "2021-11-09", "id": "0291129a-4d1a-49f0-b2f4-52b644ba6c96", "ADI_sex": "26.211111111111126", "most_likely_activity": "Health", "diagnosis_3": "Botulism", "Age": "45", "diagnosis_2": "Irritable bowel syndrome", "Interest": "teatro", "ADI_age": "33.07222222222222", "median_activity": "Health", "Gender": "male", "GLAAD": "False", "storyID": "STY1658933509", "DDI_sex": "22.607407407407408", "least_likely_activity": "School", "sarc": "False", "diagnosis_1": "Myocarditis", "ADDI_age": "37.23703703703705", "Media": "https://image.pixstory.com/Pixstory-image-165893341628070.jpeg", "Festivals": "['Climate Crisis Film Festival', 'Aesthetica Short Film Festival', 'Denver Film Festival', 'Les Gai Cine Mad', 'UK Green Film Festival', 'Leeds International Film Festival', 'Sydney Film Festival', 'Miami GEMS Film Festival', 'FILMZ - Festival des deutschen Kinos', 'Belfast Film Festival', 'Ankara Film Festival', 'Hawaii International Film Festival', 'Belo Horizonte International Short Film Festival', 'Arlington International Film Festival', 'Ojai International Film Festival', 'London Korean Film Festival', 'Mezipatra Queer Film Festival', 'Fort Lauderdale International Film Festival', 'Buffalo Dreams Fantastic Film Festival', 'Geneva International Film Festival', 'Arras Film Festival', 'MedFilm Festival', 'Thessaloniki International Film Festival', 'New Orleans Film Festival', 'Cork International Film Festival', 'Hamilton Film Festival', 'Cinanima - International Animated Film Festival', 'Mountain International Film Festival Graz', 'Brest European Short Film Festival', 'Internationale Kurzfilmtage Winterthur', 'La Cabina Festival - Festival Internacional de Mediometrajes de Val\u00e8ncia', 'Verzio International Human Rights Documentary Film Festival']", "sport_event": "['ICC World T20 (men)']", "ADDI_sex": "31.20555555555555", "Title": "Teatro, save the date tick, tick Boom", "userID": "USR1636448509", "Narrative": "STM Live e Fondazione Teatro Coccia sono lieti di annunciare la prima produzione italiana di tick, tick\u2026 BOOM!, il musical di Jonathan Larson \u2013 autore e compositore di RENT \u2013 che debutter\u00e0 al Teatro Coccia di Novara il 24 settembre 2022 e proseguir\u00e0 il suo tour nei principali teatri italiani. Gi\u00e0 in calendario le date milanesi del Teatro Franco Parenti dal 2 novembre. \n\ntick, tick\u2026 BOOM! ha conquistato il grande pubblico con la recente versione cinematografica interpretata da Andrew Garfield, candidato all\u2019Oscar 2022 e premiato ai Golden Globe Awards come miglior attore protagonista. L\u2019edizione italiana del musical vede la regia di Massimiliano Perticari e Marco Iacomelli e, nel ruolo del protagonista Jon, il giovanissimo talento italiano Nicol\u00f2 Bertonelli, reduce dal successo televisivo di Braccialetti Rossi 3", "ADL": "False", "userPrimaryID": "10534", "storyPrimaryID": "119423", "jaccard_score": 4.553391138050063e-05}