{"DDI_age": "25.175925925925913", "ADI_sex": "26.211111111111126", "most_likely_activity": "Health", "Title": "L'Italia chiude le Paralimpiadi con 7 medaglie", "accountCreateDte": "2022-01-17", "Interest": "paralimpiadi, italia", "least_likely_activity": "Hunting", "Media": "https://image.pixstory.com/Pixstory-image-16471931037493.png", "diagnosis_3": "Carbon monoxide poisoning", "ADI_age": "33.07222222222222", "diagnosis_1": "Attention deficit hyperactivity disorder", "median_activity": "Health", "GLAAD": "False", "Gender": "male", "id": "025e98d8-a360-46bc-9892-3cdf84c4f3d6", "sport_event": "['Africa Cup of Nations', 'Australian Open']", "DDI_sex": "22.607407407407408", "storyPrimaryID": "87001", "userID": "USR1642425119", "sarc": "False", "ADDI_age": "37.23703703703705", "diagnosis_2": "Hemochromatosis", "Age": "40", "ADDI_sex": "31.20555555555555", "storyID": "STY1647193606", "Narrative": "Si sono chiuse oggi le Paralimpiadi di Pechino 2022. La cerimonia di chiusura ha visto il passaggio di testimone tra la Cina e l'Italia, che ospiter\u00e0 la prossima edizione del 2026. Per gli azzurri quella di Pechino \u00e8 stata una paralimpiade molto positiva, chiusa con due ori, tre argenti e due bronzi. Protagonisti in particolare Giacomo Bertagnolli e la sua guida Andrea Ravelli, i quali nello sci alpino hanno conquistato due ori e due argenti nella categoria Vision Impaired.\nL'Italia ha cos\u00ec migliorato il bilancio di 5 medaglie della precedente edizione del 2018, giungendo undicesima in un medagliere dominato dai padroni di casa della Cina e che ha visto piazzarsi al secondo posto l'Ucraina, risultato particolarmente significativo in queste settimane che vedono il paese europeo al centro di una drammatica guerra.", "userPrimaryID": "22770", "ADL": "False", "Festivals": "", "jaccard_score": 4.553391138050063e-05}